.DS_Store
py_lpa/__init__.py
py_lpa/gmm.py
py_latent_profiles-0.4.dist-info/LICENSE.txt
py_latent_profiles-0.4.dist-info/METADATA
py_latent_profiles-0.4.dist-info/WHEEL
py_latent_profiles-0.4.dist-info/top_level.txt
py_latent_profiles-0.4.dist-info/RECORD
