Metadata-Version: 2.1
Name: py-latent-profiles
Version: 0.4
Summary: A package for running gaussian mixture models and latent profile analyses in Python
Home-page: https://github.com/johanna-einsiedler/PyGMM
Author: Johanna Einsiedler
Author-email: johanna.einsiedler@sodas.ku.dk
License: MIT
License-File: LICENSE.txt
Requires-Dist: numpy
Requires-Dist: scipy
Requires-Dist: tqdm
